tn4qa/__init__.py
tn4qa/circuit_simulator.py
tn4qa/dmrg.py
tn4qa/fidelity_metrics.py
tn4qa/mpo.py
tn4qa/mps.py
tn4qa/qi_cost_functions.py
tn4qa/qi_metrics.py
tn4qa/quantum_algorithms/__init__.py
tn4qa/quantum_algorithms/backend/base.py
tn4qa/quantum_algorithms/backend/ibm_backend.py
tn4qa/quantum_algorithms/backend/iqm_backend.py
tn4qa/quantum_algorithms/backend/qiskit_simulator.py
tn4qa/quantum_algorithms/backend/tn_backend.py
tn4qa/quantum_algorithms/base.py
tn4qa/quantum_algorithms/hamiltonian_simulation/__init__.py
tn4qa/quantum_algorithms/hamiltonian_simulation/qdrift.py
tn4qa/quantum_algorithms/hamiltonian_simulation/trotterisation.py
tn4qa/quantum_algorithms/phase_estimation/__init__.py
tn4qa/quantum_algorithms/phase_estimation/hadamard_test.py
tn4qa/quantum_algorithms/phase_estimation/qpe.py
tn4qa/quantum_algorithms/result.py
tn4qa/quantum_algorithms/selected_ci/__init__.py
tn4qa/quantum_algorithms/selected_ci/controlled_time_evolved_qsci.py
tn4qa/quantum_algorithms/selected_ci/qsci.py
tn4qa/quantum_algorithms/selected_ci/time_evolved_qsci.py
tn4qa/quantum_algorithms/utils.py
tn4qa/quantum_algorithms/variational/__init__.py
tn4qa/quantum_algorithms/variational/ansatz_circuits.py
tn4qa/quantum_algorithms/variational/classical_optimisers.py
tn4qa/quantum_algorithms/variational/vqe.py
tn4qa/tensor.py
tn4qa/tn.py
tn4qa/tn_methods/__init__.py
tn4qa/tn_methods/active_space_selection.py
tn4qa/tn_methods/approximate_diagonalisation.py
tn4qa/tn_methods/hf_suppression.py
tn4qa/tn_methods/mpo_to_circuit.py
tn4qa/tn_methods/mps_to_circuit.py
tn4qa/tn_methods/utils.py
tn4qa/utils.py
tn4qa/visualisation.py
tn4qa-0.0.4.dist-info/LICENSE
tn4qa-0.0.4.dist-info/METADATA
tn4qa-0.0.4.dist-info/WHEEL
tn4qa-0.0.4.dist-info/RECORD
